repo2docker/__init__.py
repo2docker/__main__.py
repo2docker/_version.py
repo2docker/app.py
repo2docker/docker.py
repo2docker/engine.py
repo2docker/semver.py
repo2docker/utils.py
repo2docker/buildpacks/__init__.py
repo2docker/buildpacks/_r_base.py
repo2docker/buildpacks/base.py
repo2docker/buildpacks/docker.py
repo2docker/buildpacks/python3-login
repo2docker/buildpacks/r.py
repo2docker/buildpacks/repo2docker-entrypoint
repo2docker/buildpacks/aicrowd_cacher/__init__.py
repo2docker/buildpacks/aicrowd_cacher/buildpack.py
repo2docker/buildpacks/aicrowd_cacher/query_sources.py
repo2docker/buildpacks/conda/__init__.py
repo2docker/buildpacks/conda/activate-conda.sh
repo2docker/buildpacks/conda/environment.lock
repo2docker/buildpacks/conda/environment.py-2.7.lock
repo2docker/buildpacks/conda/environment.py-2.7.yml
repo2docker/buildpacks/conda/environment.py-3.5.lock
repo2docker/buildpacks/conda/environment.py-3.5.yml
repo2docker/buildpacks/conda/environment.py-3.6.lock
repo2docker/buildpacks/conda/environment.py-3.6.yml
repo2docker/buildpacks/conda/environment.py-3.7.lock
repo2docker/buildpacks/conda/environment.py-3.7.yml
repo2docker/buildpacks/conda/environment.py-3.8.lock
repo2docker/buildpacks/conda/environment.py-3.8.yml
repo2docker/buildpacks/conda/environment.py-3.9.lock
repo2docker/buildpacks/conda/environment.py-3.9.yml
repo2docker/buildpacks/conda/environment.yml
repo2docker/buildpacks/conda/freeze.py
repo2docker/buildpacks/conda/install-base-env.bash
repo2docker/buildpacks/conda/requirements.py-3.5.pip
repo2docker/buildpacks/julia/__init__.py
repo2docker/buildpacks/julia/install-repo-dependencies.jl
repo2docker/buildpacks/julia/julia_project.py
repo2docker/buildpacks/julia/julia_require.py
repo2docker/buildpacks/legacy/__init__.py
repo2docker/buildpacks/nix/__init__.py
repo2docker/buildpacks/nix/install-nix.bash
repo2docker/buildpacks/nix/nix-shell-wrapper
repo2docker/buildpacks/pipfile/__init__.py
repo2docker/buildpacks/python/__init__.py
aicrowd_repo2docker-0.11.3.dist-info/LICENSE
aicrowd_repo2docker-0.11.3.dist-info/METADATA
aicrowd_repo2docker-0.11.3.dist-info/WHEEL
aicrowd_repo2docker-0.11.3.dist-info/entry_points.txt
aicrowd_repo2docker-0.11.3.dist-info/top_level.txt
aicrowd_repo2docker-0.11.3.dist-info/RECORD
